pyApolloClient/__init__.py
pyApolloClient/apollo_client.py
pyApolloClient/py_http_client.py
pyApolloClient/util.py
zykj_py_apollo-1.23.12.1.dist-info/METADATA
zykj_py_apollo-1.23.12.1.dist-info/WHEEL
zykj_py_apollo-1.23.12.1.dist-info/entry_points.txt
zykj_py_apollo-1.23.12.1.dist-info/top_level.txt
zykj_py_apollo-1.23.12.1.dist-info/RECORD
